django_unmanaged_forgejo/__init__.py
django_unmanaged_forgejo/apps.py
django_unmanaged_forgejo/checks.py
django_unmanaged_forgejo/models.py
django_unmanaged_forgejo/py.typed
django_unmanaged_forgejo/router.py
django_unmanaged_forgejo-0.2.0.dist-info/WHEEL
django_unmanaged_forgejo-0.2.0.dist-info/METADATA
django_unmanaged_forgejo-0.2.0.dist-info/RECORD
