Metadata-Version: 2.4
Name: django-unmanaged-forgejo
Version: 0.2.0
Summary: Unmanaged Django Models for Forgejo
Author: Paul Traylor
Author-email: Paul Traylor <kungfudiscomonkey@gmail.com>
License-Expression: MIT
Classifier: Development Status :: 3 - Alpha
Classifier: Framework :: Django :: 5.2
Classifier: Framework :: Django :: 6.0
Classifier: Programming Language :: Python :: 3.10
Classifier: Programming Language :: Python :: 3.11
Classifier: Programming Language :: Python :: 3.12
Classifier: Programming Language :: Python :: 3.13
Classifier: Programming Language :: Python :: 3.14
Classifier: Programming Language :: Python :: 3.15
Requires-Dist: django>=5.2
Requires-Python: >=3.10
Project-URL: issues, https://codeberg.org/kfdm/django-unmanaged-forgejo/issues
Project-URL: source, https://codeberg.org/kfdm/django-unmanaged-forgejo
